moviecreator/__init__.py
moviecreator/__version__.py
moviecreator/create_movie.py
movie_creator-0.1.10.dist-info/LICENSE
movie_creator-0.1.10.dist-info/METADATA
movie_creator-0.1.10.dist-info/WHEEL
movie_creator-0.1.10.dist-info/entry_points.txt
movie_creator-0.1.10.dist-info/top_level.txt
movie_creator-0.1.10.dist-info/RECORD
