Metadata-Version: 2.1
Name: movie-creator
Version: 0.1.10
Summary: Creates a movie from a list of image files.
Home-page: https://github.com/rhuygen/movie_creator
Author: Rik Huygen
Author-email: rik.huygen@kuleuven.be
License: MIT
Platform: UNKNOWN
Classifier: License :: OSI Approved :: MIT License
Classifier: Environment :: Console
Classifier: Programming Language :: Python :: 3
Classifier: Programming Language :: Python :: 3.8
Requires-Python: >=3.8.0
Requires-Dist: imageio
Requires-Dist: imageio-ffmpeg
Requires-Dist: scikit-image
Requires-Dist: rich
